sheet2db/__init__.py
sheet2db-1.0.0.dist-info/METADATA
sheet2db-1.0.0.dist-info/RECORD
sheet2db-1.0.0.dist-info/WHEEL
sheet2db-1.0.0.dist-info/top_level.txt
