Metadata-Version: 2.1
Name: sheet2db
Version: 1.0.0
Summary: A tiny library for one-way syncing the Google spreadsheet to database
Home-page: https://github.com/mingrammer/sheet2db
Author: mingrammer
Author-email: mingrammer@gmail.com
License: UNKNOWN
Keywords: spreadsheet sync
Platform: UNKNOWN
Classifier: License :: OSI Approved :: MIT License
Classifier: Programming Language :: Python
Classifier: Programming Language :: Python :: 3
Classifier: Programming Language :: Python :: 3.3
Classifier: Programming Language :: Python :: 3.4
Classifier: Programming Language :: Python :: 3.5
Classifier: Programming Language :: Python :: 3.6
Classifier: Programming Language :: Python :: 3.7
Classifier: Programming Language :: Python :: Implementation :: CPython
Classifier: Topic :: Utilities
Classifier: Topic :: Software Development :: Libraries
Requires-Python: >=3
Requires-Dist: asn1crypto (==0.24.0)
Requires-Dist: cachetools (==2.1.0)
Requires-Dist: cffi (==1.11.5)
Requires-Dist: cryptography (==2.3)
Requires-Dist: google-api-python-client (==1.7.4)
Requires-Dist: google-auth-httplib2 (==0.0.3)
Requires-Dist: google-auth (==1.5.1)
Requires-Dist: httplib2 (==0.11.3)
Requires-Dist: idna (==2.7)
Requires-Dist: oauth2client (==4.1.2)
Requires-Dist: pyasn1-modules (==0.2.2)
Requires-Dist: pyasn1 (==0.4.4)
Requires-Dist: pycparser (==2.18)
Requires-Dist: pymysql (==0.9.2)
Requires-Dist: rsa (==3.4.2)
Requires-Dist: six (==1.11.0)
Requires-Dist: uritemplate (==3.0.0)
